CytoSimplex/__init__.py
CytoSimplex/_binary.py
CytoSimplex/_normalize.py
CytoSimplex/_quaternary.py
CytoSimplex/_select_top_features.py
CytoSimplex/_similarity.py
CytoSimplex/_ternary.py
CytoSimplex/_util.py
CytoSimplex/_velo_grid.py
CytoSimplex/tests/__init__.py
CytoSimplex/tests/test_CytoSimplex.py
cytosimplex-0.1.0.dist-info/LICENSE
cytosimplex-0.1.0.dist-info/WHEEL
cytosimplex-0.1.0.dist-info/METADATA
cytosimplex-0.1.0.dist-info/RECORD
